ai/__init__.py
ai/starlake/__init__.py
ai/starlake/aws/__init__.py
ai/starlake/aws/starlake_fargate_helper.py
ai/starlake/common/__init__.py
ai/starlake/dataset/__init__.py
ai/starlake/dataset/starlake_dataset.py
ai/starlake/gcp/__init__.py
ai/starlake/gcp/starlake_dataproc_cluster_config.py
ai/starlake/job/__init__.py
ai/starlake/job/spark_config.py
ai/starlake/job/starlake_job.py
ai/starlake/job/starlake_options.py
ai/starlake/job/starlake_pre_load_strategy.py
ai/starlake/odbc/__init__.py
ai/starlake/odbc/starlake_session.py
ai/starlake/odbc/starlake_sql_job.py
ai/starlake/odbc/starlake_sql_orchestration.py
ai/starlake/odbc/starlake_sql_task.py
ai/starlake/orchestration/__init__.py
ai/starlake/orchestration/__main__.py
ai/starlake/orchestration/starlake_dependencies.py
ai/starlake/orchestration/starlake_orchestration.py
ai/starlake/orchestration/starlake_schedules.py
starlake_orchestration-0.4.3.dist-info/licenses/LICENSE
starlake_orchestration-0.4.3.dist-info/METADATA
starlake_orchestration-0.4.3.dist-info/WHEEL
starlake_orchestration-0.4.3.dist-info/top_level.txt
starlake_orchestration-0.4.3.dist-info/RECORD
