Metadata-Version: 2.4
Name: starlake-orchestration
Version: 0.4.3
Summary: Starlake Python Distribution For orchestration
Author: Stéphane Manciot
Author-email: stephane.manciot@gmail.com
License: Apache 2.0
License-File: LICENSE
Provides-Extra: airflow
Requires-Dist: starlake-airflow~=0.4; extra == "airflow"
Provides-Extra: dagster
Requires-Dist: starlake-dagster~=0.4; extra == "dagster"
Provides-Extra: snowflake
Requires-Dist: starlake-snowflake~=0.3; extra == "snowflake"
Provides-Extra: shell
Provides-Extra: gcp
Provides-Extra: aws
Provides-Extra: azure
Dynamic: author
Dynamic: author-email
Dynamic: description
Dynamic: description-content-type
Dynamic: license
Dynamic: license-file
Dynamic: provides-extra
Dynamic: summary
